configuretron/__init__.py
configuretron/__main__.py
configuretron/cli.py
configuretron/configuretron.py
configuretron-0.3.0.dist-info/AUTHORS.rst
configuretron-0.3.0.dist-info/LICENSE
configuretron-0.3.0.dist-info/METADATA
configuretron-0.3.0.dist-info/WHEEL
configuretron-0.3.0.dist-info/entry_points.txt
configuretron-0.3.0.dist-info/top_level.txt
configuretron-0.3.0.dist-info/RECORD
