Metadata-Version: 2.1
Name: configuretron
Version: 0.3.0
Summary: Configuration and Secrets for Python applications
Home-page: https://github.com/channelcat/configuretron
Author: Channel Cat
Author-email: channelcat@gmail.com
License: MIT license
Keywords: configuretron
Classifier: Development Status :: 2 - Pre-Alpha
Classifier: Intended Audience :: Developers
Classifier: License :: OSI Approved :: MIT License
Classifier: Natural Language :: English
Classifier: Programming Language :: Python :: 3
Classifier: Programming Language :: Python :: 3.9
Classifier: Programming Language :: Python :: 3.10
Classifier: Programming Language :: Python :: 3.11
Requires-Python: >=3.9
License-File: LICENSE
License-File: AUTHORS.rst
Requires-Dist: Click >=7.0
Requires-Dist: PyYAML >=5.3.1
Requires-Dist: rsa >=4.9
